{
  "program_name": "Health Policy and Administration, B.S. (Health and Human Development)",
  "subplan": null,
  "catalog_year": "2024",
  "degree": "B.S.",
  "total_credits": 120.0,
  "source": "https://bulletins.psu.edu/undergraduate/colleges/health-human-development/health-policy-administration-bs/",
  "scraped": true,
  "semesters": [
    {
      "year": 1,
      "term_season": "FA",
      "credits": 16.0,
      "slots": [
        {
          "type": "choose_one",
          "codes": [
            "BISC 4",
            "BIOL 141",
            "BIOL 161",
            "BBH 101"
          ],
          "credits": 3.0
        },
        {
          "type": "gen_ed",
          "category": "GS",
          "credits": 3.0
        },
        {
          "type": "course",
          "code": "HPA 101",
          "credits": 3.0
        },
        {
          "type": "gen_ed",
          "category": "GWS",
          "credits": 3.0
        },
        {
          "type": "gen_ed",
          "category": null,
          "credits": 1.0
        },
        {
          "type": "gen_ed",
          "category": "GA",
          "credits": 3.0
        }
      ]
    },
    {
      "year": 1,
      "term_season": "SP",
      "credits": 15.0,
      "slots": [
        {
          "type": "course",
          "code": "HPA 210",
          "credits": 3.0
        },
        {
          "type": "gen_ed",
          "category": null,
          "credits": 3.0
        },
        {
          "type": "gen_ed",
          "category": "GWS",
          "credits": 3.0
        },
        {
          "type": "gen_ed",
          "category": "GH",
          "credits": 3.0
        },
        {
          "type": "gen_ed",
          "category": null,
          "credits": 3.0
        }
      ]
    },
    {
      "year": 2,
      "term_season": "FA",
      "credits": 15.0,
      "slots": [
        {
          "type": "course",
          "code": "HPA 211",
          "credits": 3.0
        },
        {
          "type": "gen_ed",
          "category": "GQ",
          "credits": 3.0
        },
        {
          "type": "gen_ed",
          "category": null,
          "credits": 3.0
        },
        {
          "type": "gen_ed",
          "category": null,
          "credits": 3.0
        },
        {
          "type": "gen_ed",
          "category": null,
          "credits": 3.0
        }
      ]
    },
    {
      "year": 2,
      "term_season": "SP",
      "credits": 15.0,
      "slots": [
        {
          "type": "course",
          "code": "HPA 200",
          "credits": 3.0
        },
        {
          "type": "course",
          "code": "HPA 332",
          "credits": 3.0
        },
        {
          "type": "course",
          "code": "HPA 301W",
          "credits": 3.0
        },
        {
          "type": "course",
          "code": "HPA 390W",
          "credits": 3.0
        },
        {
          "type": "gen_ed",
          "category": null,
          "credits": 3.0
        }
      ]
    },
    {
      "year": 3,
      "term_season": "FA",
      "credits": 15.0,
      "slots": [
        {
          "type": "course",
          "code": "HPA 310",
          "credits": 3.0
        },
        {
          "type": "choose_one",
          "codes": [
            "CMPSC 101",
            "CMPSC 203",
            "MIS 204"
          ],
          "credits": 3.0
        },
        {
          "type": "gen_ed",
          "category": null,
          "credits": 3.0
        },
        {
          "type": "gen_ed",
          "category": null,
          "credits": 3.0
        },
        {
          "type": "gen_ed",
          "category": null,
          "credits": 3.0
        }
      ]
    },
    {
      "year": 3,
      "term_season": "SP",
      "credits": 15.0,
      "slots": [
        {
          "type": "course",
          "code": "HPA 311",
          "credits": 3.0
        },
        {
          "type": "course",
          "code": "HPA 400",
          "credits": 3.0
        },
        {
          "type": "gen_ed",
          "category": null,
          "credits": 3.0
        },
        {
          "type": "gen_ed",
          "category": null,
          "credits": 3.0
        },
        {
          "type": "gen_ed",
          "category": null,
          "credits": 3.0
        }
      ]
    },
    {
      "year": 3,
      "term_season": "FA",
      "credits": 3.0,
      "slots": [
        {
          "type": "course",
          "code": "HPA 395",
          "credits": 3.0
        }
      ]
    },
    {
      "year": 4,
      "term_season": "FA",
      "credits": 14.0,
      "slots": [
        {
          "type": "gen_ed",
          "category": "GWS",
          "credits": 3.0
        },
        {
          "type": "course",
          "code": "HPA 400",
          "credits": 3.0
        },
        {
          "type": "elective",
          "label": "Elective",
          "credits": 2.0
        },
        {
          "type": "gen_ed",
          "category": null,
          "credits": 3.0
        },
        {
          "type": "gen_ed",
          "category": null,
          "credits": 3.0
        }
      ]
    },
    {
      "year": 4,
      "term_season": "SP",
      "credits": 12.0,
      "slots": [
        {
          "type": "course",
          "code": "HPA 455",
          "credits": 3.0
        },
        {
          "type": "course",
          "code": "HPA 400",
          "credits": 3.0
        },
        {
          "type": "gen_ed",
          "category": null,
          "credits": 3.0
        },
        {
          "type": "gen_ed",
          "category": null,
          "credits": 3.0
        }
      ]
    }
  ]
}