{
  "program_name": "Sustainability, Society, and Environmental Geography, B.A.",
  "subplan": null,
  "catalog_year": "2024",
  "degree": "B.A.",
  "total_credits": 123.0,
  "source": "https://bulletins.psu.edu/undergraduate/colleges/earth-mineral-sciences/sustainability-society-environmental-geography-ba/",
  "scraped": true,
  "semesters": [
    {
      "year": 1,
      "term_season": "FA",
      "credits": 16.0,
      "slots": [
        {
          "type": "course",
          "code": "EMSC 100S",
          "credits": 3.0,
          "gen_ed": "GWS"
        },
        {
          "type": "gen_ed",
          "category": "GQ",
          "credits": 3.0
        },
        {
          "type": "gen_ed",
          "category": null,
          "credits": 3.0
        },
        {
          "type": "pool",
          "ref": "world_language",
          "label": "World Language Level 1",
          "credits": 4.0
        },
        {
          "type": "choose_one",
          "codes": [
            "GEOG 210",
            "GEOG 230"
          ],
          "credits": 3.0
        }
      ]
    },
    {
      "year": 1,
      "term_season": "SP",
      "credits": 16.0,
      "slots": [
        {
          "type": "gen_ed",
          "category": "GQ",
          "credits": 3.0
        },
        {
          "type": "pool",
          "ref": "world_language",
          "label": "World Language Level 2",
          "credits": 4.0
        },
        {
          "type": "choose_one",
          "codes": [
            "GEOG 210",
            "GEOG 230"
          ],
          "credits": 3.0
        },
        {
          "type": "gen_ed",
          "category": "GWS",
          "credits": 3.0
        },
        {
          "type": "gen_ed",
          "category": null,
          "credits": 3.0
        }
      ]
    },
    {
      "year": 2,
      "term_season": "FA",
      "credits": 16.0,
      "slots": [
        {
          "type": "pool",
          "ref": "world_language",
          "label": "World Language Level 3",
          "credits": 4.0
        },
        {
          "type": "course",
          "code": "GEOG 340",
          "credits": 3.0
        },
        {
          "type": "gen_ed",
          "category": null,
          "credits": 3.0
        },
        {
          "type": "gen_ed",
          "category": null,
          "credits": 3.0
        },
        {
          "type": "gen_ed",
          "category": null,
          "credits": 3.0
        }
      ]
    },
    {
      "year": 2,
      "term_season": "SP",
      "credits": 16.0,
      "slots": [
        {
          "type": "course",
          "code": "GEOG 344",
          "credits": 3.0
        },
        {
          "type": "course",
          "code": "GEOG 390",
          "credits": 1.0
        },
        {
          "type": "gen_ed",
          "category": null,
          "credits": 3.0
        },
        {
          "type": "gen_ed",
          "category": null,
          "credits": 3.0
        },
        {
          "type": "gen_ed",
          "category": null,
          "credits": 3.0
        },
        {
          "type": "gen_ed",
          "category": null,
          "credits": 3.0
        }
      ]
    },
    {
      "year": 3,
      "term_season": "FA",
      "credits": 15.0,
      "slots": [
        {
          "type": "gen_ed",
          "category": null,
          "credits": 3.0
        },
        {
          "type": "gen_ed",
          "category": null,
          "credits": 3.0
        },
        {
          "type": "gen_ed",
          "category": null,
          "credits": 3.0
        },
        {
          "type": "gen_ed",
          "category": null,
          "credits": 3.0
        },
        {
          "type": "gen_ed",
          "category": null,
          "credits": 3.0
        }
      ]
    },
    {
      "year": 3,
      "term_season": "SP",
      "credits": 14.0,
      "slots": [
        {
          "type": "gen_ed",
          "category": null,
          "credits": 3.0
        },
        {
          "type": "gen_ed",
          "category": null,
          "credits": 3.0
        },
        {
          "type": "gen_ed",
          "category": null,
          "credits": 3.0
        },
        {
          "type": "gen_ed",
          "category": null,
          "credits": 3.0
        },
        {
          "type": "gen_ed",
          "category": null,
          "credits": 2.0
        }
      ]
    },
    {
      "year": 4,
      "term_season": "FA",
      "credits": 15.0,
      "slots": [
        {
          "type": "gen_ed",
          "category": null,
          "credits": 3.0
        },
        {
          "type": "choose_one",
          "codes": [
            "EMSC 299",
            "EMSC 470W",
            "GEOG 199",
            "GEOG 299",
            "GEOG 399",
            "GEOG 493",
            "GEOG 494",
            "GEOG 494H",
            "GEOG 495",
            "GEOG 495B",
            "GEOG 495G",
            "GEOG 499"
          ],
          "credits": 3.0
        },
        {
          "type": "gen_ed",
          "category": null,
          "credits": 3.0
        },
        {
          "type": "gen_ed",
          "category": null,
          "credits": 3.0
        },
        {
          "type": "gen_ed",
          "category": null,
          "credits": 3.0
        }
      ]
    },
    {
      "year": 4,
      "term_season": "SP",
      "credits": 15.0,
      "slots": [
        {
          "type": "course",
          "code": "GEOG 440",
          "credits": 3.0
        },
        {
          "type": "gen_ed",
          "category": null,
          "credits": 3.0
        },
        {
          "type": "gen_ed",
          "category": null,
          "credits": 3.0
        },
        {
          "type": "gen_ed",
          "category": null,
          "credits": 3.0
        },
        {
          "type": "elective",
          "label": "Elective",
          "credits": 3.0
        }
      ]
    }
  ]
}